{
    "fechaDescarga": "29/12/2023, 08:50:32",
    "json_original": {
        "tipoNorma": "",
        "nroNorma": "",
        "anioNorma": 0,
        "nombreNorma": "",
        "leyenda": "  ",
        "fechaPromulgacion": "",
        "fechaPublicacion": "",
        "vistos": "  ",
        "tituloArticulo": "  T\u00cdTULO IV - SEGURIDAD Y DEFENSA\r\n  CAP\u00cdTULO VII - CONSOLIDACI\u00d3N DE DEUDA DEL SECTOR P\u00daBLICO NACIONAL",
        "nombreArticulo": "",
        "textoArticulo": "",
        "notasArticulo": "",
        "firmantes": ""
    },
    "numeroArticulo": "331",
    "seccionArticulo": "IV",
    "capituloArticulo": "VII",
    "textoArticulo": "",
    "notasArticulo": "",
    "textoOriginal": "",
    "textoModificado": "Reuni\u00f3n o manifestaci\u00f3n. A efectos de este Cap\u00edtulo de la ley, enti\u00e9ndase por \u201creuni\u00f3n\u201d o \u201cmanifestaci\u00f3n\u201d a la congregaci\u00f3n intencional y temporal de tres (3) o m\u00e1s personas en un espacio p\u00fablico con el prop\u00f3sito del ejercicio de los derechos aludidos en la presente."
}