{
    "fechaDescarga": "29/12/2023, 08:50:32",
    "json_original": {
        "tipoNorma": "",
        "nroNorma": "",
        "anioNorma": 0,
        "nombreNorma": "",
        "leyenda": "  ",
        "fechaPromulgacion": "",
        "fechaPublicacion": "",
        "vistos": "  ",
        "tituloArticulo": "  T\u00cdTULO II - Reforma del Estado\r\n  CAP\u00cdTULO IV - . Empleo p\u00fablico",
        "nombreArticulo": "",
        "textoArticulo": "",
        "notasArticulo": "",
        "firmantes": ""
    },
    "numeroArticulo": "49",
    "seccionArticulo": "II",
    "capituloArticulo": "IV",
    "textoArticulo": "",
    "notasArticulo": "",
    "textoOriginal": "Art\u00edculo 32. \u2014 Son causales para imponer cesant\u00eda:\n\na) Inasistencias injustificadas que excedan de 10 (diez) d\u00edas discontinuos, en los 12 (doce) meses inmediatos anteriores.\n\nb) Abandono de servicio, el cual se considerar\u00e1 consumado cuando el agente registrare m\u00e1s de cinco (5) inasistencias continuas sin causa que lo justifique y fuera intimado previamente en forma fehaciente a retomar sus tareas.\n\nc) Infracciones reiteradas en el cumplimiento de sus tareas, que hayan dado lugar a treinta (30) d\u00edas de suspensi\u00f3n en los doce meses anteriores.\n\nd) Concurso civil o quiebra no causal, salvo casos debidamente justificados por la autoridad administrativa.\n\ne) Incumplimiento de los deberes establecidos en los art\u00edculos 23 y 24 cuando por la magnitud y gravedad de la falta as\u00ed correspondiere.\n\nf) Delito doloso no referido a la Administraci\u00f3n P\u00fablica, cuando por sus circunstancias afecte el prestigio de la funci\u00f3n o del agente.\n\ng) Calificaciones deficientes como resultado de evaluaciones que impliquen desempe\u00f1o ineficaz durante tres (3) a\u00f1os consecutivos o cuatro (4) alternados en los \u00faltimos diez (10) a\u00f1os de servicio y haya contado con oportunidades de capacitaci\u00f3n adecuada para el desempe\u00f1o de las tareas.\n\nEn todos los casos podr\u00e1 considerarse la solicitud de rehabilitaci\u00f3n a partir de los dos (2) a\u00f1os de consentido el acto por el que se dispusiera la cesant\u00eda o de declarada firme la sentencia judicial, en su caso.\n",
    "textoModificado": "ART\u00cdCULO 32.- Son causales para imponer la cesant\u00eda: a) inasistencias injustificadas que excedan de cinco (5) d\u00edas discontinuos, en los doce (12) meses inmediatos anteriores; b) abandono de servicio, el cual se considerar\u00e1 consumado cuando el agente registrare m\u00e1s de tres (3) inasistencias continuas sin causa que lo justifique y fuera intimado previamente en forma fehaciente a retomar sus tareas; c) infracciones reiteradas en el cumplimiento de sus tareas, que hayan dado lugar a treinta (30) d\u00edas de suspensi\u00f3n en los doce (12) meses anteriores; d) concurso civil o quiebra no causal, salvo casos debidamente justificados por la autoridad administrativa; e) incumplimiento de los deberes establecidos en los art\u00edculos 23 y 24 cuando por la magnitud y gravedad de la falta as\u00ed correspondiere; f) delito doloso no referido a la Administraci\u00f3n P\u00fablica, cuando por sus\ncircunstancias afecte el prestigio de la funci\u00f3n o del agente. g) Calificaciones deficientes como resultado de evaluaciones que impliquen desempe\u00f1o ineficaz durante dos (2) a\u00f1os consecutivos o tres (3) alternados en los \u00faltimos diez (10) a\u00f1os de servicio y haya contado con oportunidades de capacitaci\u00f3n adecuada para el desempe\u00f1o de las tareas. En todos los casos podr\u00e1 considerarse la solicitud de rehabilitaci\u00f3n a partir de los dos (2) a\u00f1os de consentido el acto por el que se dispusiera la cesant\u00eda o de declarada firme la sentencia judicial, en su caso."
}