{
    "fechaDescarga": "29/12/2023, 08:50:32",
    "json_original": {
        "tipoNorma": "",
        "nroNorma": "",
        "anioNorma": 0,
        "nombreNorma": "",
        "leyenda": "  ",
        "fechaPromulgacion": "",
        "fechaPublicacion": "",
        "vistos": "  ",
        "tituloArticulo": "  T\u00cdTULO V - JUSTICIA\r\n  CAP\u00cdTULO XIII - JUICIO POR JURADOS",
        "nombreArticulo": "",
        "textoArticulo": "",
        "notasArticulo": "",
        "firmantes": ""
    },
    "numeroArticulo": "442",
    "seccionArticulo": "V",
    "capituloArticulo": "XIII",
    "textoArticulo": "",
    "notasArticulo": "",
    "textoOriginal": "",
    "textoModificado": "Apru\u00e9bese el R\u00e9gimen de Juicio por Jurados que se adjunta como ANEXO VI (IF-2023- 153006832-APN-SSAL#SLYT).\nT\u00cdTULO VI - INTERIOR, AMBIENTE, TURISMO Y DEPORTE\nCAP\u00cdTULO I - DEL SISTEMA ELECTORAL\n\nSecci\u00f3n I - Circunscripciones uninominales"
}