{
    "fechaDescarga": "29/12/2023, 08:50:32",
    "json_original": {
        "tipoNorma": "",
        "nroNorma": "",
        "anioNorma": 0,
        "nombreNorma": "",
        "leyenda": "  ",
        "fechaPromulgacion": "",
        "fechaPublicacion": "",
        "vistos": "  ",
        "tituloArticulo": "  T\u00cdTULO III - REORGANIZACI\u00d3N ECON\u00d3MICA\r\n  CAP\u00cdTULO VII - CONSOLIDACI\u00d3N DE DEUDA DEL SECTOR P\u00daBLICO NACIONAL",
        "nombreArticulo": "",
        "textoArticulo": "",
        "notasArticulo": "",
        "firmantes": ""
    },
    "numeroArticulo": "241",
    "seccionArticulo": "III",
    "capituloArticulo": "VII",
    "textoArticulo": "",
    "notasArticulo": "",
    "textoOriginal": "",
    "textoModificado": "Adhesi\u00f3n a Convenci\u00f3n. La REP\u00daBLICA ARGENTINA adhiere a la Convenci\u00f3n Internacional sobre la Protecci\u00f3n de Nuevas Variedades Vegetales (1991).\n\nSecci\u00f3n III \u2013 R\u00e9gimen Federal de pesca (Ley 24922)"
}