{
    "fechaDescarga": "29/12/2023, 08:50:32",
    "json_original": {
        "tipoNorma": "",
        "nroNorma": "",
        "anioNorma": 0,
        "nombreNorma": "",
        "leyenda": "  ",
        "fechaPromulgacion": "",
        "fechaPublicacion": "",
        "vistos": "  ",
        "tituloArticulo": "  T\u00cdTULO V - JUSTICIA\r\n  CAP\u00cdTULO IX - REGISTRO DE LA PROPIEDAD INMUEBLE",
        "nombreArticulo": "",
        "textoArticulo": "",
        "notasArticulo": "",
        "firmantes": ""
    },
    "numeroArticulo": "425",
    "seccionArticulo": "V",
    "capituloArticulo": "IX",
    "textoArticulo": "",
    "notasArticulo": "",
    "textoOriginal": "",
    "textoModificado": "Sustit\u00fayese el art\u00edculo 3\u00b0 de la Ley N\u00b017.801 por el siguiente:\n\n\u201cART\u00cdCULO 3\u00b0.- Para que los documentos mencionados en el art\u00edculo anterior puedan ser inscriptos o anotados, deber\u00e1n reunir los siguientes requisitos:\n\na) Estar constituidos por escritura notarial o resoluci\u00f3n judicial o administrativa, seg\u00fan legalmente corresponda;\n\nb) Tener las formalidades establecidas por las leyes y estar autorizados sus originales o copias por quien est\u00e9 facultado para hacerlo;\n\nc) Revestir el car\u00e1cter de aut\u00e9nticos y hacer fe por s\u00ed mismo o con otros complementarios en cuanto al contenido que sea objeto de la registraci\u00f3n, sirviendo inmediatamente de t\u00edtulo al dominio, derecho real o asiento practicable.\n\nPara los casos de excepci\u00f3n que establezcan las leyes especiales, podr\u00e1n ser inscriptos o anotados los instrumentos privados, siempre que la firma de sus otorgantes est\u00e9 certificada por escribano p\u00fablico, juez de paz o funcionario competente\u201d."
}