{
    "fechaDescarga": "29/12/2023, 08:50:32",
    "json_original": {
        "tipoNorma": "",
        "nroNorma": "",
        "anioNorma": 0,
        "nombreNorma": "",
        "leyenda": "  ",
        "fechaPromulgacion": "",
        "fechaPublicacion": "",
        "vistos": "  ",
        "tituloArticulo": "  T\u00cdTULO V - JUSTICIA\r\n  CAP\u00cdTULO II - DEFENSA NACIONAL",
        "nombreArticulo": "",
        "textoArticulo": "",
        "notasArticulo": "",
        "firmantes": ""
    },
    "numeroArticulo": "392",
    "seccionArticulo": "V",
    "capituloArticulo": "II",
    "textoArticulo": "",
    "notasArticulo": "",
    "textoOriginal": "ART\u00cdCULO 2038.- Constituci\u00f3n. A los fines de la divisi\u00f3n jur\u00eddica del edificio, el titular de dominio o los cond\u00f3minos deben redactar, por escritura p\u00fablica, el reglamento de propiedad horizontal, que debe inscribirse en el registro inmobiliario.\n\nEl reglamento de propiedad horizontal se integra al t\u00edtulo suficiente sobre la unidad funcional.\n",
    "textoModificado": "ART\u00cdCULO 2038.- Constituci\u00f3n. A los fines de la divisi\u00f3n jur\u00eddica del edificio, el titular de dominio o los cond\u00f3minos deben redactar, por escritura p\u00fablica, el reglamento de propiedad horizontal, que debe inscribirse en el registro inmobiliario.\n\nEl reglamento de propiedad horizontal se integra al t\u00edtulo suficiente sobre la unidad funcional."
}