{
    "fechaDescarga": "29/12/2023, 08:50:32",
    "json_original": {
        "tipoNorma": "",
        "nroNorma": "",
        "anioNorma": 0,
        "nombreNorma": "",
        "leyenda": "  ",
        "fechaPromulgacion": "",
        "fechaPublicacion": "",
        "vistos": "  ",
        "tituloArticulo": "  T\u00cdTULO III - REORGANIZACI\u00d3N ECON\u00d3MICA\r\n  CAP\u00cdTULO IV - OPERACIONES DE CR\u00c9DITO P\u00daBLICO",
        "nombreArticulo": "",
        "textoArticulo": "",
        "notasArticulo": "",
        "firmantes": ""
    },
    "numeroArticulo": "209",
    "seccionArticulo": "III",
    "capituloArticulo": "IV",
    "textoArticulo": "",
    "notasArticulo": "",
    "textoOriginal": "",
    "textoModificado": "En la publicidad de las prestaciones o servicios de cualquier tipo en los niveles nacional, provincial, municipal y de la Ciudad Aut\u00f3noma de Buenos Aires que sean de libre acceso o atenci\u00f3n por parte de los ciudadanos no podr\u00e1 utilizarse la palabra \u201cgratuito\u201d o similares debi\u00e9ndose aclarar que se trata de una prestaci\u00f3n o servicio de libre acceso solventado con los tributos de los contribuyentes.\n\nSecci\u00f3n IX. Otras Medidas Fiscales"
}