{
    "fechaDescarga": "29/12/2023, 08:50:32",
    "json_original": {
        "tipoNorma": "",
        "nroNorma": "",
        "anioNorma": 0,
        "nombreNorma": "",
        "leyenda": "  ",
        "fechaPromulgacion": "",
        "fechaPublicacion": "",
        "vistos": "  ",
        "tituloArticulo": "  T\u00cdTULO VI - INTERIOR, AMBIENTE, TURISMO Y DEPORTE\r\n  CAP\u00cdTULO XIII - JUICIO POR JURADOS",
        "nombreArticulo": "",
        "textoArticulo": "",
        "notasArticulo": "",
        "firmantes": ""
    },
    "numeroArticulo": "448",
    "seccionArticulo": "VI",
    "capituloArticulo": "XIII",
    "textoArticulo": "",
    "notasArticulo": "",
    "textoOriginal": "Art\u00edculo 163.- En las convocatorias de cada distrito electoral se fijar\u00e1 el n\u00famero de Diputados Nacionales, titulares y suplentes. A estos fines se establecer\u00e1 el n\u00famero de suplentes que a continuaci\u00f3n se expresa:\n\nCuando se elijan 2 titulares: 2 suplentes\n\nCuando se elijan de 3 a 5 titulares: 3 suplentes\n\nCuando se elijan 6 y 7 titulares: 4 suplentes\n\nCuando se elijan 8 titulares: 5 suplentes\n\nCuando se elijan 9 y 10 titulares: 6 suplentes\n\nCuando se elijan de 11 a 20 titulares: 8 suplentes\n\nCuando se elijan 21 titulares o m\u00e1s: 10 suplentes.\n\n(Art\u00edculo sustituido por art. 2 de la Ley N\u00b0 24.444 B.O. 19/1/1995).\n",
    "textoModificado": "ART\u00cdCULO 163.- Las listas de candidatos se integrar\u00e1n con un candidato titular y un suplente, los cuales deber\u00e1n ser de diferente g\u00e9nero."
}