{
    "fechaDescarga": "29/12/2023, 08:50:32",
    "json_original": {
        "tipoNorma": "",
        "nroNorma": "",
        "anioNorma": 0,
        "nombreNorma": "",
        "leyenda": "  ",
        "fechaPromulgacion": "",
        "fechaPublicacion": "",
        "vistos": "  ",
        "tituloArticulo": "",
        "nombreArticulo": "",
        "textoArticulo": "",
        "notasArticulo": "",
        "firmantes": ""
    },
    "numeroArticulo": "123",
    "seccionArticulo": "III",
    "capituloArticulo": "IV",
    "textoArticulo": "",
    "notasArticulo": "",
    "textoOriginal": "",
    "textoModificado": "Sanci\u00f3n por incumplimiento del plazo de transferencia. Si el contribuyente incumpliera con la obligaci\u00f3n de transferir el bien dentro del plazo m\u00e1ximo previsto en el art\u00edculo 121 y no resultar\u00e1 aplicable la excepci\u00f3n por imposibilidad de transferencia del art\u00edculo 122, deber\u00e1 pagar un Impuesto Especial de Regularizaci\u00f3n adicional equivalente al CINCO POR CIENTO (5%) del valor del bien en cuesti\u00f3n, calculado de acuerdo a las reglas del art\u00edculo 118.\nEfectos de la regularizaci\u00f3n."
}